Workbook

Sheet Target_Comps
B1: Company_ID | C1: Company_Name | D1: Ticker | E1: Sector | F1: Business_Segment | G1: Revenue_Current | H1: Revenue_Growth_Pct | I1: EBITDA_Margin_Pct | J1: EBITDA | K1: Net_Income | L1: Total_Debt | M1: Market_Cap | O1: Enterprise_Value | P1: EV_Rev_Multiple | Q1: EV_EBITDA_Multiple
B2: 1 | C2: PubMatic Inc | D2: PUBM | E2: Technology | F2: AdTech & Analytics | G2: 228.38 | H2: 0.09 | I2: =J2/G2 -> 0.1508013 | J2: 34.44 | K2: -7.25 | L2: 45.86 | M2: 419.82 | O2: =M2+L2 -> 465.68 | P2: =O2/G2 -> 2.0390577 | Q2: =O2/J2 -> 13.521487
B3: 2 | C3: Ribbon Communications Inc | D3: RBBN | E3: Technology | F3: Cloud Infrastructure | G3: 868.59 | H3: 0.01 | I3: =J3/G3 -> 0.11244661 | J3: 97.67 | K3: -43.06 | L3: 383.67 | M3: 502.42 | O3: =M3+L3 -> 886.09 | P3: =O3/G3 -> 1.0201476 | Q3: =O3/J3 -> 9.0722842
B4: 3 | C4: Red Violet Inc | D4: RDVT | E4: Technology | F4: Data Analytics | G4: 86.42 | H4: 0.25 | I4: =J4/G4 -> 0.25792641 | J4: 22.29 | K4: 11.2 | L4: 2 | M4: 760.48 | O4: =M4+L4 -> 762.48 | P4: =O4/G4 -> 8.8229576 | Q4: =O4/J4 -> 34.207268
B5: 4 | C5: Rimini Street Inc | D5: RMNI | E5: Technology | F5: Legacy ERP | G5: 425.96 | H5: -0.01 | I5: =J5/G5 -> 0.10782703 | J5: 45.93 | K5: 43.03 | L5: 827.25 | M5: 352.24 | O5: =M5+L5 -> 1179.49 | P5: =O5/G5 -> 2.7690159 | Q5: =O5/J5 -> 25.680165
B6: 5 | C6: SmartRent Inc | D6: SMRT | E6: Technology | F6: PropTech SaaS | G6: 151.22 | H6: -0.26 | I6: =J6/G6 -> -0.2645814 | J6: -40.01 | K6: -68.74 | L6: 8.12 | M6: 320.7 | O6: =M6+L6 -> 328.82 | P6: =O6/G6 -> 2.1744478 | Q6: =O6/J6 -> -8.2184454
B7: 6 | C7: Sprout Social Inc | D7: SPT | E7: Technology | F7: Social Media Tools | G7: 443.75 | H7: 0.22 | I7: =J7/G7 -> -0.06235493 | J7: -27.67 | K7: -47 | L7: 43.29 | M7: 592.62 | O7: =M7+L7 -> 635.91 | P7: =O7/G7 -> 1.4330366 | Q7: =O7/J7 -> -22.98193
B8: 7 | C8: Par Technology Corp | D8: PAR | E8: Technology | F8: Vertical SaaS | G8: 440.45 | H8: 0.26 | I8: =J8/G8 -> -0.020660688 | J8: -9.1 | K8: -88.81 | L8: 376.67 | M8: 1410 | O8: =M8+L8 -> 1786.67 | P8: =O8/G8 -> 4.056465 | Q8: =O8/J8 -> -196.33736
B9: 8 | C9: Pagerduty Inc | D9: PD | E9: Technology | F9: DevOps & Cloud | G9: 489.21 | H9: 0.09 | I9: =J9/G9 -> 0.036569163 | J9: 17.89 | K9: 152.23 | L9: 463.65 | M9: 1090 | O9: =M9+L9 -> 1553.65 | P9: =O9/G9 -> 3.1758345 | Q9: =O9/J9 -> 86.844606
B10: 9 | C10: Porch Group Inc | D10: PRCH | E10: Technology | F10: Vertical SaaS | G10: 442.48 | H10: 0.02 | I10: =J10/G10 -> 0.21709456 | J10: 96.06 | K10: 30.59 | L10: 406.18 | M10: 1010 | O10: =M10+L10 -> 1416.18 | P10: =O10/G10 -> 3.2005514 | Q10: =O10/J10 -> 14.742661
B11: 10 | C11: Pros Holdings Inc | D11: PRO | E11: Technology | F11: AI & Machine Learning | G11: 351.68 | H11: 0.09 | I11: =J11/G11 -> -0.023714741 | J11: -8.34 | K11: -11.66 | L11: 300.9 | M11: 1120 | O11: =M11+L11 -> 1420.9 | P11: =O11/G11 -> 4.0403207 | Q11: =O11/J11 -> -170.3717
B12: 11 | C12: CloudScale | D12: PVT | E12: Technology | F12: AI & Machine Learning | G12: 150.5 | H12: 0.35 | I12: =J12/G12 -> 0.22 | J12: 33.11 | K12: 18.5 | L12: 25 | M12: 0 | O12: =MEDIAN(O2:O11) -> 1032.79 | P12: =MEDIAN(P2:P11) -> 2.9724252 | Q12: =MEDIAN(Q2:Q11) -> 11.296885 | R12: Median
B13: 12 | C13: DataVantage | D13: PVT | E13: Technology | F13: Cybersecurity | G13: 319.66 | H13: 0.25 | I13: =J13/G13 -> 0.18019145 | J13: 57.6 | K13: 40.2 | L13: 52 | M13: 0
B14: 13 | C14: NeuralFlow | D14: PVT | E14: Technology | F14: Legacy ERP | G14: 32.33 | H14: 0.6 | I14: =J14/G14 -> -0.74234457 | J14: -24 | K14: -30 | L14: 14 | M14: 0 | O14: =_xlfn.PERCENTILE.INC(O2:O11, 0.25) -> 667.5525 | P14: =_xlfn.PERCENTILE.INC(P2:P11, 0.25) -> 2.0729052 | Q14: =_xlfn.PERCENTILE.INC(Q2:Q11, 0.25) -> -19.291059 | R14: Low Multiple
B15: 14 | C15: Securify | D15: PVT | E15: Technology | F15: AI & Machine Learning | G15: 152.33 | H15: 0.45 | I15: =J15/G15 -> -0.19694085 | J15: -30 | K15: -45 | L15: 43 | M15: 0 | O15: =_xlfn.PERCENTILE.INC(O2:O11, 0.75) -> 1419.72 | P15: =_xlfn.PERCENTILE.INC(P2:P11, 0.75) -> 3.8303784 | Q15: =_xlfn.PERCENTILE.INC(Q2:Q11, 0.75) -> 22.945789 | R15: High Multiple
B16: 15 | C16: CodeStream | D16: PVT | E16: Technology | F16: DevOps & Cloud | G16: 499.66 | H16: 0.05 | I16: =J16/G16 -> 0.35023816 | J16: 175 | K16: 120 | L16: 102 | M16: 0
B17: 16 | C17: StackSync | D17: PVT | E17: Technology | F17: AI & Machine Learning | G17: 402.33 | H17: 0.02 | I17: =J17/G17 -> 0.31317575 | J17: 126 | K17: 90 | L17: 152 | M17: 0
B18: 17 | C18: VantaGuard | D18: PVT | E18: Technology | F18: Cybersecurity | G18: 299.66 | H18: 0.1 | I18: =J18/G18 -> 0.12013615 | J18: 36 | K18: -10 | L18: 467 | M18: 0
B19: 18 | C19: OmniLogic | D19: PVT | E19: Technology | F19: Legacy ERP | G19: 502.33 | H19: 0.08 | I19: =J19/G19 -> 0.16423467 | J19: 82.5 | K19: 20 | L19: 638 | M19: 0
B20: 19 | C20: FlowState | D20: PVT | E20: Technology | F20: Vertical SaaS | G20: 72.33 | H20: 0.12 | I20: =J20/G20 -> 0.082953131 | J20: 6 | K20: 2 | L20: 50 | M20: 0
B21: 20 | C21: CipherLock | D21: PVT | E21: Technology | F21: Cybersecurity | G21: 249.66 | H21: 0.15 | I21: =J21/G21 -> 0.080108948 | J21: 20 | K21: 10 | L21: 80 | M21: 0
B22: 21 | C22: DocuWave | D22: PVT | E22: Technology | F22: Vertical SaaS | G22: 373.24 | H22: 0.23 | I22: =J22/G22 -> 0.12236095 | J22: 45.67 | K22: 34.12 | L22: 12.45 | M22: 0
B23: 22 | C23: TaskForce | D23: PVT | E23: Technology | F23: AI & Machine Learning | G23: 793.6 | H23: 0.18 | I23: =J23/G23 -> 0.028843246 | J23: 22.89 | K23: 15.43 | L23: 5.67 | M23: 0
B24: 23 | C24: MetricStream | D24: PVT | E24: Technology | F24: Legacy ERP | G24: 198.4 | H24: -0.04 | I24: =J24/G24 -> -0.062197581 | J24: -12.34 | K24: -18.9 | L24: 45.2 | M24: 0
B25: 24 | C25: OptiNet | D25: PVT | E25: Technology | F25: DevOps & Cloud | G25: 448.33 | H25: 0.41 | I25: =J25/G25 -> 0.19878215 | J25: 89.12 | K25: 67.45 | L25: 102.3 | M25: 0
B26: 25 | C26: QuantData | D26: PVT | E26: Technology | F26: AI & Machine Learning | G26: 592.33 | H26: 0.11 | I26: =J26/G26 -> 0.058345855 | J26: 34.56 | K26: 28.1 | L26: 15.8 | M26: 0
B27: 26 | C27: CyberShield | D27: PVT | E27: Technology | F27: Cybersecurity | G27: 468.33 | H27: 0.09 | I27: =J27/G27 -> 0.1212393 | J27: 56.78 | K27: 42.3 | L27: 210.45 | M27: 0
... B51: 50 | C51: PrimeLayer | D51: PVT | E51: Technology | F51: AI & Machine Learning | G51: 566.75 | H51: 0.24 | I51: =J51/G51 -> 0.029554477 | J51: 16.75 | K51: 12.6 | L51: 8.5 | M51: 0

Sheet Peer_Screening
A1: Company_ID | B1: Company_Name | C1: Business_Segment | D1: Revenue_Current | E1: EBITDA | F1: Total_Debt | G1: Leverage_Ratio | H1: Rule_of_40_Score
A2: 24 | B2: OptiNet | C2: DevOps & Cloud | D2: 448.33 | E2: 89.12 | F2: 102.3 | G2: 1.14789 | H2: 61
A3: 11 | B3: CloudScale | C3: AI & Machine Learning | D3: 150.5 | E3: 33.11 | F3: 25 | G3: 0.755059 | H3: 57
A4: 29 | B4: CoreBridge | C4: Vertical SaaS | D4: 297.6 | E4: -8.9 | F4: 34.2 | G4: -3.842697 | H4: 52
A5: 43 | B5: TechNova | C5: AI & Machine Learning | D5: 373.36 | E5: -6.7 | F5: 28.4 | G5: -4.238806 | H5: 46
A6: 12 | B6: DataVantage | C6: Cybersecurity | D6: 319.66 | E6: 57.6 | F6: 52 | G6: 0.902778 | H6: 43

Sheet Valuation_Model
B1: Scenario | C1: Low Case | D1: Base Case | E1: High Case
B2: EV/Revenue Multiple | C2: =Target_Comps!P14 -> 2.0729052 | D2: =Target_Comps!P12 -> 2.9724252 | E2: =Target_Comps!P15 -> 3.8303784
B3: EV/EBITDA Multiple | C3: =Target_Comps!Q3 -> 9.0722842 | D3: =Target_Comps!Q12 -> 11.296885 | E3: =Target_Comps!Q15 -> 22.945789
B4: Implied Value (Rev Based) | C4: =Target_Comps!$G$25*Valuation_Model!C2 -> 929.34561 | D4: =Target_Comps!$G$25*Valuation_Model!D2 -> 1332.6274 | E4: =Target_Comps!$G$25*Valuation_Model!E2 -> 1717.2736
B5: Implied Value (EBITDA Based) | C5: =Target_Comps!$J$25*Valuation_Model!C3 -> 808.52197 | D5: =Target_Comps!$J$25*Valuation_Model!D3 -> 1006.7784 | E5: =Target_Comps!$J$25*Valuation_Model!E3 -> 2044.9287
B6: Average Value | C6: =AVERAGE(C4:C5) -> 868.93379 | D6: =AVERAGE(D4:D5) -> 1169.7029 | E6: =AVERAGE(E4:E5) -> 1881.1011
B7: Less: Illiquidity Discount | C7: =C6*-0.25 -> -217.23345 | D7: =D6*-0.25 -> -292.42573 | E7: =E6*-0.25 -> -470.27529
B8: Final Equity Value | C8: =SUM(C6:C7) -> 651.70034 | D8: =SUM(D6:D7) -> 877.27718 | E8: =SUM(E6:E7) -> 1410.8259
B10: Company | D10: OptiNet
B11: Revenue ($M) | D11: =Target_Comps!G25 -> 448.33
B12: EBITDA ($M) | D12: =Target_Comps!J25 -> 89.12
